data_verifier/__init__.py
data_verifier/base.py
data_verifier/exceptions/__init__.py
data_verifier/exceptions/exception.py
data_verifier/identities/__init__.py
data_verifier/identities/ahrefs/__init__.py
data_verifier/identities/ahrefs/ahrefs_details.py
data_verifier/identities/ahrefs/exceptions.py
data_verifier/identities/ahrefs/templates.py
data_verifier/identities/get_12th_board/__init__.py
data_verifier/identities/get_12th_board/get_12th_result.py
data_verifier/identities/lsa_academy/__init__.py
data_verifier/identities/lsa_academy/template.py
data_verifier/identities/lsa_academy/course_details/__init__.py
data_verifier/identities/lsa_academy/course_details/course_detail.py
data_verifier/identities/lsa_academy/drop_course/__init__.py
data_verifier/identities/lsa_academy/drop_course/drop.py
data_verifier/identities/lsa_academy/forgot_password/__init__.py
data_verifier/identities/lsa_academy/forgot_password/forgot.py
data_verifier/identities/lsa_academy/logins/__init__.py
data_verifier/identities/lsa_academy/logins/login.py
data_verifier/identities/lsa_academy/print_acknowledgement/__init__.py
data_verifier/identities/lsa_academy/print_acknowledgement/acknowledgement.py
data_verifier/identities/lsa_academy/register_course/__init__.py
data_verifier/identities/lsa_academy/register_course/register.py
data_verifier/identities/metro/__init__.py
data_verifier/identities/metro/Delhi/__init__.py
data_verifier/identities/metro/Delhi/delhi_metro.py
data_verifier/identities/rm_internships/__init__.py
data_verifier/identities/rm_internships/exceptions.py
data_verifier/identities/rm_internships/templates.py
data_verifier/identities/rm_internships/utils.py
data_verifier/identities/rm_internships/applications/__init__.py
data_verifier/identities/rm_internships/applications/my_aplication.py
data_verifier/identities/rm_internships/jobs/__init__.py
data_verifier/identities/rm_internships/jobs/job_list.py
data_verifier/identities/rm_internships/login/__init__.py
api_manager_verifier-0.1.22.dist-info/LICENSE.txt
api_manager_verifier-0.1.22.dist-info/METADATA
api_manager_verifier-0.1.22.dist-info/WHEEL
api_manager_verifier-0.1.22.dist-info/top_level.txt
api_manager_verifier-0.1.22.dist-info/RECORD
